twibint-0.1.0.dist-info/METADATA
twibint-0.1.0.dist-info/WHEEL
twibint-0.1.0.dist-info/license_files/LICENSE
twibint/__init__.py
twibint/twibint.cpython-310-x86_64-linux-gnu.so
twibint-0.1.0.dist-info/RECORD
