Metadata-Version: 2.1
Name: twibint
Version: 0.1.0
Requires-Dist: maturin ==1.1.0
Requires-Dist: pytest ==7.3.2
License-File: LICENSE
